{
"type": "FeatureCollection",
                                                                                
"features": [
{ "type": "Feature", "properties": { "id": 4, "nom": "École Jacques Prévert", "img": "ecole.png" }, "geometry": { "type": "Point", "coordinates": [ -1.287521341393422, 47.093648106175507 ] } }
]
}